{
  "sort": [
    {
      "mid": 1,
      "tid": 123456797,
      "amount": 12.32,
      "narration": 11234684654
    },
    {
      "mid": 2,
      "tid": 123456794,
      "amount": 12.32,
      "narration": 11234684654
    },
    {
      "mid": 3,
      "tid": 123456791,
      "amount": 12.32,
      "narration": 11234684654
    },
    {
      "mid": 3,
      "tid": 123456791,
      "amount": 12.32,
      "narration": 11234684654
    },
    {
      "mid": 1,
      "tid": 123456797,
      "amount": 12.32,
      "narration": 11234684654
    },
    {
      "mid": 2,
      "tid": 123456794,
      "amount": 12.32,
      "narration": 11234684654
    },
    {
      "mid": 1,
      "tid": 123456797,
      "amount": 12.32,
      "narration": 11234684654
    },
    {
      "mid": 3,
      "tid": 123456791,
      "amount": 12.32,
      "narration": 11234684654
    },
    {
      "mid": 1,
      "tid": 123456795,
      "amount": 12.32,
      "narration": 11234684654
    },
    {
      "mid": 1,
      "tid": 123456795,
      "amount": 12.32,
      "narration": 11234684654
    },
    {
      "mid": 3,
      "tid": 123456791,
      "amount": 12.32,
      "narration": 11234684654
    }
  ]
}